datamusepython/DatamusePython.py
datamusepython/__init__.py
datamuse_python-1.4.8.dist-info/METADATA
datamuse_python-1.4.8.dist-info/WHEEL
datamuse_python-1.4.8.dist-info/top_level.txt
datamuse_python-1.4.8.dist-info/RECORD
