Metadata-Version: 2.1
Name: datamuse-python
Version: 1.4.8
Summary: A collection of functions using the Datamuse API.
Home-page: https://github.com/Animesh0203/datamuse-python
Author: Animesh Srivastava
Author-email: animeshsrivastava2003@email.com
Requires-Dist: requests >=2.0.0
Requires-Dist: beautifulsoup4 >=4.0.0
